query_tool/__init__.py
query_tool/frontend/dist/index.html
query_tool/frontend/dist/vite.svg
query_tool/frontend/dist/assets/index-d081bea5.css
query_tool/frontend/dist/assets/index-e2f3e6a4.js
query_tool/services/__init__.py
query_tool/services/dimension_service.py
query_tool/services/entities_service.py
query_tool/services/filters_service.py
query_tool/services/query_tool_factory.py
query_tool/services/query_tool_service.py
query_tool/services/register.py
bp_query_tool-1.0.3.dist-info/LICENSE
bp_query_tool-1.0.3.dist-info/METADATA
bp_query_tool-1.0.3.dist-info/WHEEL
bp_query_tool-1.0.3.dist-info/top_level.txt
bp_query_tool-1.0.3.dist-info/RECORD
