Metadata-Version: 2.1
Name: bp-query-tool
Version: 1.0.3
Summary: Query tool to generate query from selection
Home-page: UNKNOWN
Author: Bluepinapple
Author-email: vivek.sthul@bluepinapple.com
License: UNKNOWN
Platform: UNKNOWN
Requires-Python: >=3.8.10
Requires-Dist: streamlit (>=1.20.0)
